log_aggregator/__init__.py
log_aggregator/colors.py
log_aggregator/conf_loader.py
log_aggregator/free_space_checker.py
log_aggregator/gopher_version_manager.py
log_aggregator/gui.py
log_aggregator/gui_test.py
log_aggregator/image_sequence_unwarper.py
log_aggregator/opt_parser.py
log_aggregator/specific_entries_manager.py
log_aggregator/tar_manager.py
log_aggregator-0.50.data/scripts/log_aggregator
log_aggregator-0.50.dist-info/DESCRIPTION.rst
log_aggregator-0.50.dist-info/METADATA
log_aggregator-0.50.dist-info/RECORD
log_aggregator-0.50.dist-info/WHEEL
log_aggregator-0.50.dist-info/metadata.json
log_aggregator-0.50.dist-info/top_level.txt
