Metadata-Version: 2.0
Name: log-aggregator
Version: 0.50
Summary: Create a configurable Tarball of various files in the file system
Home-page: https://github.com/yotabits/log_aggregator
Author: Thomas Kostas
Author-email: tkostas75@gmail.com
License: MIT
Platform: UNKNOWN
Classifier: Development Status :: 3 - Alpha
Classifier: Intended Audience :: Developers
Classifier: Topic :: Software Development :: Build Tools
Classifier: License :: OSI Approved :: MIT License
Classifier: Programming Language :: Python :: 2.7
Requires-Dist: appjar
Requires-Dist: gopher-robot-version
Requires-Dist: pillow
Requires-Dist: psutil
Requires-Dist: pycurl
Requires-Dist: tqdm
